pygpudrive/__init__.py
pygpudrive/env/README.md
pygpudrive/env/__init__.py
pygpudrive/env/base_env.py
pygpudrive/env/config.py
pygpudrive/env/env_jax.py
pygpudrive/env/env_torch.py
pygpudrive/env/scene_selector.py
pygpudrive/env/viz.py
pygpudrive/env/wrappers/__init__.py
pygpudrive/env/wrappers/jaxmarl_wrapper.py
pygpudrive/env/wrappers/sb3_wrapper.py
pygpudrive/utils/__init__.py
gpudrive-0.1.0.dist-info/LICENSE
gpudrive-0.1.0.dist-info/METADATA
gpudrive-0.1.0.dist-info/WHEEL
gpudrive-0.1.0.dist-info/RECORD
