Metadata-Version: 2.1
Name: gpudrive
Version: 0.1.0
Summary: 
Author: Saman Kazemkhani, Aarav Pandya, Daphne Cornelisse, Eugene Vinitsky
Requires-Python: >=3.11,<4.0
Classifier: Programming Language :: Python :: 3
Classifier: Programming Language :: Python :: 3.11
Classifier: Programming Language :: Python :: 3.12
Requires-Dist: numpy (>=1.26.4,<2.0.0)
Requires-Dist: pytest (>=8.2.1,<9.0.0)
Requires-Dist: torch (>=2.2.1,<3.0.0)
